LICENSE
README.md
setup.py
librarypython/__init__.py
librarypython/librarypythoncodigos.py
librarypython.egg-info/PKG-INFO
librarypython.egg-info/SOURCES.txt
librarypython.egg-info/dependency_links.txt
librarypython.egg-info/not-zip-safe
librarypython.egg-info/requires.txt
librarypython.egg-info/top_level.txt
librarypython/spam/__init__.py
librarypython/spam/db.py
librarypython/spam/enviador_de_email.py
librarypython/spam/main.py
librarypython/spam/modelos.py
librarypython/tests/__init__.py
librarypython/tests/test_enviador_de_email.py
librarypython/tests/test_exemplo.py
librarypython/tests/test_spam/__init__.py
librarypython/tests/test_spam/conftest.py
librarypython/tests/test_spam/test_envio_para_base_de_usuarios.py
librarypython/tests/test_spam/test_librarypythoncodigos.py
librarypython/tests/test_spam/test_usuarios.py